gemini_parallel/__init__.py
gemini_parallel/cli.py
gemini_parallel/gemini_media_processor.py
gemini_parallel/gemini_parallel.py
gemini_parallel/gemini_tts.py
gemini_parallel/prompt_types.py
gemini_parallel-0.8.0.dist-info/licenses/LICENSE
gemini_parallel-0.8.0.dist-info/METADATA
gemini_parallel-0.8.0.dist-info/WHEEL
gemini_parallel-0.8.0.dist-info/entry_points.txt
gemini_parallel-0.8.0.dist-info/top_level.txt
gemini_parallel-0.8.0.dist-info/RECORD
