Metadata-Version: 2.4
Name: gemini-parallel
Version: 0.8.0
Summary: Simplified Sequential Processor for Google Gemini API
Requires-Python: >=3.10
License-File: LICENSE
Requires-Dist: google-api-core>=2.25.0
Requires-Dist: google-genai>=1.18.0
Requires-Dist: python-dotenv>=1.1.0
Dynamic: license-file
